{
  "date": "2026-05-02",
  "changes": {
    "6002": {
      "added": [
        {
          "appId": 6762445294,
          "name": "Dice Roller: Random Roller",
          "publisher": "DataX Power",
          "icon": "https://is1-ssl.mzstatic.com/image/thumb/Purple221/v4/35/41/1b/35411bee-b414-bedb-917e-c6e8edae0efd/AppIcon-0-0-1x_U007emarketing-0-7-0-85-220.png/180x180bb.png",
          "rating": 0,
          "ratingCount": 0,
          "price": "0.00",
          "rank": 216,
          "category": "6002"
        },
        {
          "appId": 6738370584,
          "name": "Sophon - Secure Cloud Storage",
          "publisher": "New Sophon Technology Limited",
          "icon": "https://is1-ssl.mzstatic.com/image/thumb/Purple211/v4/75/cd/f3/75cdf306-04cc-433f-a290-1087c5c2b7ea/AppIcon-0-0-1x_U007epad-0-1-0-0-85-220.jpeg/180x180bb.png",
          "rating": 4.3,
          "ratingCount": 6,
          "price": "0.00",
          "rank": 273,
          "category": "6002"
        },
        {
          "appId": 385894596,
          "name": "Remote Mouse",
          "publisher": "耀 阮",
          "icon": "https://is1-ssl.mzstatic.com/image/thumb/Purple211/v4/3a/1e/25/3a1e254f-b6e9-0f97-55b5-d527fd379e66/AppIcon-0-0-1x_U007emarketing-0-8-0-85-220.png/180x180bb.png",
          "rating": 4.6,
          "ratingCount": 18200,
          "price": "0.00",
          "rank": 334,
          "category": "6002"
        },
        {
          "appId": 6761963008,
          "name": "Dazzloop",
          "publisher": "家保 张",
          "icon": "https://is1-ssl.mzstatic.com/image/thumb/Purple221/v4/1e/86/96/1e8696de-41db-4406-43eb-a720a6e8c12a/AppIcon-0-1x_U007ephone-0-1-0-85-220-0.png/180x180bb.png",
          "rating": 0,
          "ratingCount": 0,
          "price": "0.00",
          "rank": 359,
          "category": "6002"
        },
        {
          "appId": 763638165,
          "name": "IPVanish: IP Location Changer",
          "publisher": "IPVanish, Inc.",
          "icon": "https://is1-ssl.mzstatic.com/image/thumb/Purple221/v4/d8/db/10/d8db1052-148c-8141-5d3b-5a586088b23f/AppIcon-0-0-1x_U007emarketing-0-8-0-85-220.png/100x100bb.jpg",
          "rating": 4.6,
          "ratingCount": 104000,
          "price": "0.00",
          "rank": 389,
          "category": "6002"
        },
        {
          "appId": 1151964202,
          "name": "HuntFishNY",
          "publisher": "Gordon-Darby, Inc.",
          "icon": "https://is1-ssl.mzstatic.com/image/thumb/Purple211/v4/6f/c9/42/6fc942aa-e736-7b8e-ac73-34ee5ae695f1/AppIcon-0-0-1x_U007emarketing-0-8-0-85-220.png/180x180bb.png",
          "rating": 2.2,
          "ratingCount": 277,
          "price": "0.00",
          "rank": 407,
          "category": "6002"
        },
        {
          "appId": 6762169860,
          "name": "Jtnzlt- AI Dress Try On",
          "publisher": "鑫 刘",
          "icon": "https://is1-ssl.mzstatic.com/image/thumb/Purple211/v4/0a/a1/a4/0aa1a430-ef11-e9fa-06ce-877d3483bfde/AppIcon-0-0-1x_U007ephone-0-1-85-220.jpeg/180x180bb.png",
          "rating": 0,
          "ratingCount": 0,
          "price": "0.00",
          "rank": 413,
          "category": "6002"
        },
        {
          "appId": 6747024744,
          "name": "iMoveGo - Change location",
          "publisher": "Haokai Wang",
          "icon": "https://is1-ssl.mzstatic.com/image/thumb/Purple211/v4/85/94/15/85941556-f1e5-fb71-7825-fd34443be2ab/AppIcon-1x_U007ephone-0-1-0-85-220-0.png/180x180bb.png",
          "rating": 1.7,
          "ratingCount": 6,
          "price": "0.00",
          "rank": 425,
          "category": "6002"
        },
        {
          "appId": 1635152504,
          "name": "Netboom: Gaming & Community",
          "publisher": "怡羽 潘",
          "icon": "https://is1-ssl.mzstatic.com/image/thumb/Purple221/v4/7d/49/24/7d49249d-3a1e-7b95-39a1-77e773447063/AppIcon-1x_U007ephone-0-1-0-sRGB-85-220-0.png/180x180bb.png",
          "rating": 3.7,
          "ratingCount": 2562,
          "price": "0.00",
          "rank": 431,
          "category": "6002"
        },
        {
          "appId": 6473857677,
          "name": "CenterPoint Energy My Account",
          "publisher": "CenterPoint Energy Inc",
          "icon": "https://is1-ssl.mzstatic.com/image/thumb/Purple221/v4/5a/18/3b/5a183bce-635d-42c0-52d1-1f7cd0f664f8/AppIcon-0-0-1x_U007emarketing-0-7-0-85-220.png/180x180bb.png",
          "rating": 2.6,
          "ratingCount": 78,
          "price": "0.00",
          "rank": 433,
          "category": "6002"
        },
        {
          "appId": 6739610993,
          "name": "Find My Phone By Clapping",
          "publisher": "Hieu Tran Thanh",
          "icon": "https://is1-ssl.mzstatic.com/image/thumb/Purple221/v4/a9/31/23/a9312341-3b09-0e0c-dc73-3ef1aa3d39be/AppIcon-0-0-1x_U007emarketing-0-11-0-85-220.png/180x180bb.png",
          "rating": 4.4,
          "ratingCount": 6125,
          "price": "0.00",
          "rank": 438,
          "category": "6002"
        },
        {
          "appId": 666921945,
          "name": "Reliant",
          "publisher": "Reliant Energy Retail Holdings, LLC",
          "icon": "https://is1-ssl.mzstatic.com/image/thumb/Purple221/v4/de/ed/32/deed32c6-569c-8197-d860-ea40a798a8f7/AppIcon-0-0-1x_U007emarketing-0-8-0-sRGB-85-220.png/180x180bb.png",
          "rating": 4.9,
          "ratingCount": 18800,
          "price": "0.00",
          "rank": 453,
          "category": "6002"
        },
        {
          "appId": 1463342498,
          "name": "NextDNS",
          "publisher": "nextdns Inc.",
          "icon": "https://is1-ssl.mzstatic.com/image/thumb/Purple211/v4/78/8d/0a/788d0ab3-364d-8c86-22c0-05e886e31bce/AppIcon-0-0-1x_U007emarketing-0-8-0-85-220.png/180x180bb.png",
          "rating": 4.3,
          "ratingCount": 921,
          "price": "0.00",
          "rank": 454,
          "category": "6002"
        },
        {
          "appId": 1621229655,
          "name": "Sony | BRAVIA Connect",
          "publisher": "Sony Corporation",
          "icon": "https://is1-ssl.mzstatic.com/image/thumb/Purple211/v4/26/6a/1d/266a1d0d-81fb-4eab-fd1c-49e5841531c0/AppIcon-0-0-1x_U007emarketing-0-11-0-85-220.png/180x180bb.png",
          "rating": 4.5,
          "ratingCount": 7739,
          "price": "0.00",
          "rank": 456,
          "category": "6002"
        },
        {
          "appId": 6504548974,
          "name": "HelloBlink",
          "publisher": "Shenzhen Yihengke Electronic Technology Co.,Ltd.",
          "icon": "https://is1-ssl.mzstatic.com/image/thumb/Purple211/v4/21/64/aa/2164aa14-c073-0482-6b08-0d6183ed4f9a/AppIcon-0-0-1x_U007ephone-0-1-0-85-220.png/180x180bb.png",
          "rating": 4.6,
          "ratingCount": 38000,
          "price": "0.00",
          "rank": 460,
          "category": "6002"
        },
        {
          "appId": 6449592297,
          "name": "Laxasfit",
          "publisher": "Shenzhen United Power Technology Co., Ltd.",
          "icon": "https://is1-ssl.mzstatic.com/image/thumb/Purple211/v4/47/20/43/4720438c-554d-8698-7993-c861fe40e3a3/AppIcon-0-0-1x_U007emarketing-0-8-0-0-sRGB-85-220.png/180x180bb.png",
          "rating": 3.4,
          "ratingCount": 222,
          "price": "0.00",
          "rank": 466,
          "category": "6002"
        },
        {
          "appId": 1474675452,
          "name": "*** - Fast & Secure *** Proxy",
          "publisher": "Minoti Inc",
          "icon": "https://is1-ssl.mzstatic.com/image/thumb/Purple211/v4/b9/ed/77/b9ed7770-290f-f1a8-c164-23e062b3b80f/AppIcon-0-0-1x_U007emarketing-0-8-0-85-220.png/180x180bb.png",
          "rating": 4.6,
          "ratingCount": 52100,
          "price": "0.00",
          "rank": 468,
          "category": "6002"
        },
        {
          "appId": 6739811401,
          "name": "Xfinity Call Guard",
          "publisher": "Comcast",
          "icon": "https://is1-ssl.mzstatic.com/image/thumb/Purple211/v4/f9/15/e0/f915e04e-e05d-ac99-fe2f-30e50c8549d8/AppIcon-0-0-1x_U007ephone-0-1-85-220.png/180x180bb.png",
          "rating": 3,
          "ratingCount": 92,
          "price": "0.00",
          "rank": 469,
          "category": "6002"
        },
        {
          "appId": 1435063223,
          "name": "Lawfully Case Tracker",
          "publisher": "Lawfully, Inc.",
          "icon": "https://is1-ssl.mzstatic.com/image/thumb/Purple211/v4/f3/1a/f9/f31af91a-781d-5858-2313-44fcc55302b3/AppIcon_Eagle_2-0-0-1x_U007epad-0-1-0-85-220.png/180x180bb.png",
          "rating": 4.8,
          "ratingCount": 158000,
          "price": "0.00",
          "rank": 470,
          "category": "6002"
        },
        {
          "appId": 6742210155,
          "name": "Antova",
          "publisher": "RESIDENCE XII",
          "icon": "https://is1-ssl.mzstatic.com/image/thumb/Purple221/v4/af/2c/95/af2c95cd-89fa-468c-f985-c189354a52ed/AppIcon-0-0-1x_U007epad-0-1-0-85-220.png/180x180bb.png",
          "rating": 3.6,
          "ratingCount": 722,
          "price": "0.00",
          "rank": 471,
          "category": "6002"
        },
        {
          "appId": 870099476,
          "name": "Copy My Data - Smart Transfer",
          "publisher": "Red Sky Labs, S.L.",
          "icon": "https://is1-ssl.mzstatic.com/image/thumb/Purple221/v4/38/33/a9/3833a99d-e29e-e33a-e63b-7e25c76c5c3c/AppIcon-0-0-1x_U007emarketing-0-7-0-85-220.png/180x180bb.png",
          "rating": 4.5,
          "ratingCount": 16100.000000000002,
          "price": "0.00",
          "rank": 473,
          "category": "6002"
        },
        {
          "appId": 6742729924,
          "name": "BitDynamic:Real-Time Translate",
          "publisher": "Bit Dynamic (Shenzhen) Technology Co., Ltd.",
          "icon": "https://is1-ssl.mzstatic.com/image/thumb/Purple221/v4/44/9e/12/449e127a-7f6e-d2eb-20ab-4e1482a27761/AppIcon-0-0-1x_U007ephone-0-1-0-85-220.png/180x180bb.png",
          "rating": 4.3,
          "ratingCount": 4006,
          "price": "0.00",
          "rank": 475,
          "category": "6002"
        },
        {
          "appId": 1156220055,
          "name": "CleanPay Mobile",
          "publisher": "KioSoft Technologies LLC",
          "icon": "https://is1-ssl.mzstatic.com/image/thumb/Purple211/v4/3e/b8/8d/3eb88d7d-8025-6a32-8c7f-027573a999f6/AppIcon-0-0-1x_U007emarketing-0-6-0-0-85-220.png/180x180bb.png",
          "rating": 4.5,
          "ratingCount": 11399.999999999998,
          "price": "0.00",
          "rank": 476,
          "category": "6002"
        },
        {
          "appId": 6443559566,
          "name": "Boost Cleaner",
          "publisher": "THREE PANDA DIGITAL LIMITED",
          "icon": "https://is1-ssl.mzstatic.com/image/thumb/Purple221/v4/ce/6d/eb/ce6debac-05c1-c457-4a74-9efbf8724616/AppIcon-0-0-1x_U007ephone-0-11-0-85-220.png/180x180bb.png",
          "rating": 4.3,
          "ratingCount": 29,
          "price": "0.00",
          "rank": 477,
          "category": "6002"
        },
        {
          "appId": 6760337872,
          "name": "Glamf - AI Court Art",
          "publisher": "Jiangxi Xinlong Dragon Lion Sports Co., Ltd",
          "icon": "https://is1-ssl.mzstatic.com/image/thumb/Purple211/v4/32/49/33/3249335d-8120-ac48-7795-9391f46bb337/AppIcon-1x_U007ephone-0-1-85-220-0.png/180x180bb.png",
          "rating": 5,
          "ratingCount": 28,
          "price": "0.00",
          "rank": 478,
          "category": "6002"
        },
        {
          "appId": 6745781559,
          "name": "StreamHub 2025",
          "publisher": "Sindha Pritiben",
          "icon": "https://is1-ssl.mzstatic.com/image/thumb/Purple221/v4/e5/a4/92/e5a49295-8c7c-4029-ecfd-831fa9b1db3c/AppIcon-0-0-1x_U007ephone-0-1-85-220.jpeg/180x180bb.png",
          "rating": 0,
          "ratingCount": 0,
          "price": "0.00",
          "rank": 484,
          "category": "6002"
        },
        {
          "appId": 1447578249,
          "name": "biubiu-Game booster",
          "publisher": "广州宁静海信息科技有限公司",
          "icon": "https://is1-ssl.mzstatic.com/image/thumb/Purple211/v4/5e/c3/ec/5ec3ecd8-31a9-19b2-f85d-06c969696e4d/AppIcon-0-1x_U007emarketing-0-8-0-85-220-0.png/180x180bb.png",
          "rating": 4.6,
          "ratingCount": 16000,
          "price": "0.00",
          "rank": 486,
          "category": "6002"
        },
        {
          "appId": 1452925688,
          "name": "Eversource Energy",
          "publisher": "Eversource Energy Service Company",
          "icon": "https://is1-ssl.mzstatic.com/image/thumb/Purple221/v4/e0/9d/d9/e09dd955-f5a6-a634-1cba-adfc960908f1/AppIcon-0-0-1x_U007emarketing-0-8-0-85-220.png/180x180bb.png",
          "rating": 4.9,
          "ratingCount": 32100,
          "price": "0.00",
          "rank": 487,
          "category": "6002"
        },
        {
          "appId": 529855219,
          "name": "Entergy",
          "publisher": "Entergy Services, LLC",
          "icon": "https://is1-ssl.mzstatic.com/image/thumb/Purple221/v4/8d/d6/6b/8dd66ba9-4d73-1c6f-57c0-795a3b90544c/ic_app_prod-0-0-1x_U007emarketing-0-8-0-sRGB-85-220.png/180x180bb.png",
          "rating": 2.7,
          "ratingCount": 1387,
          "price": "0.00",
          "rank": 488,
          "category": "6002"
        },
        {
          "appId": 960998088,
          "name": "JustIN Mobile",
          "publisher": "Salto Systems",
          "icon": "https://is1-ssl.mzstatic.com/image/thumb/Purple211/v4/b3/da/74/b3da7498-1d37-81bb-b558-c76f1390fdf6/AppIcon-0-1x_U007emarketing-0-0-0-7-0-0-85-220-0.png/180x180bb.png",
          "rating": 4.4,
          "ratingCount": 1990,
          "price": "0.00",
          "rank": 492,
          "category": "6002"
        },
        {
          "appId": 6443806453,
          "name": "Sunrun",
          "publisher": "Sunrun Inc.",
          "icon": "https://is1-ssl.mzstatic.com/image/thumb/Purple221/v4/57/0a/1f/570a1f0c-c976-a068-7912-6dd28d0038a3/AppIcon-0-0-1x_U007epad-0-11-0-85-220.png/180x180bb.png",
          "rating": 4.5,
          "ratingCount": 2507,
          "price": "0.00",
          "rank": 494,
          "category": "6002"
        },
        {
          "appId": 6752901737,
          "name": "KeepClean AI: Storage Cleaner",
          "publisher": "Olosera Limited",
          "icon": "https://is1-ssl.mzstatic.com/image/thumb/Purple221/v4/bb/a2/3c/bba23ccb-eb59-90e2-2c71-7b06bb044742/AppIcon-0-0-1x_U007ephone-0-1-85-220.png/180x180bb.png",
          "rating": 4.2,
          "ratingCount": 3966,
          "price": "0.00",
          "rank": 497,
          "category": "6002"
        },
        {
          "appId": 553317645,
          "name": "MySCE",
          "publisher": "Southern California Edison",
          "icon": "https://is1-ssl.mzstatic.com/image/thumb/Purple211/v4/d1/58/b8/d158b84c-8360-9f17-557b-1c5056a8c37b/AppIcon-0-0-1x_U007emarketing-0-6-0-85-220.png/180x180bb.png",
          "rating": 1.9,
          "ratingCount": 1305,
          "price": "0.00",
          "rank": 499,
          "category": "6002"
        },
        {
          "appId": 1577663728,
          "name": "Creality Cloud - 3D Printing",
          "publisher": "CREALITY 3D (HK) TECHNOLOGY LIMITED",
          "icon": "https://is1-ssl.mzstatic.com/image/thumb/Purple211/v4/ba/ef/3a/baef3aa7-ae97-f2bd-2c64-f7cdf3a201c3/AppIcon2022_us-0-0-1x_U007epad-0-1-0-sRGB-85-220.png/180x180bb.png",
          "rating": 4.6,
          "ratingCount": 6454,
          "price": "0.00",
          "rank": 500,
          "category": "6002"
        }
      ],
      "removed": [
        {
          "appId": 6745930154,
          "name": "Color Grab (color detection)",
          "publisher": "Ashvin Kevadiya",
          "icon": "https://is1-ssl.mzstatic.com/image/thumb/Purple221/v4/9f/9a/7a/9f9a7ad7-e1d5-9096-5741-708d6315710c/AppIcon-1x_U007emarketing-0-11-0-85-220-0.png/180x180bb.png",
          "rating": 3.4,
          "ratingCount": 27,
          "price": "0.00",
          "rank": 337,
          "category": "6002"
        },
        {
          "appId": 6760695167,
          "name": "Tali-",
          "publisher": "Razira Qubfa",
          "icon": "https://is1-ssl.mzstatic.com/image/thumb/Purple221/v4/29/f2/69/29f269dc-82b3-3174-63eb-7d9ae86d42bb/AppIcon-1x_U007ephone-0-1-85-220-0.png/180x180bb.png",
          "rating": 0,
          "ratingCount": 0,
          "price": "0.00",
          "rank": 382,
          "category": "6002"
        },
        {
          "appId": 1506827551,
          "name": "gov.br",
          "publisher": "Servicos e Informacoes do Brasil",
          "icon": "https://is1-ssl.mzstatic.com/image/thumb/Purple221/v4/af/69/b0/af69b04a-dd6c-0096-76e7-2a8b17aab02a/AppIcon-0-0-1x_U007emarketing-0-11-0-85-220.png/180x180bb.png",
          "rating": 4.8,
          "ratingCount": 64100,
          "price": "0.00",
          "rank": 387,
          "category": "6002"
        },
        {
          "appId": 6760697284,
          "name": "Amor!",
          "publisher": "SHAMROCK IDIOMAS S.L.",
          "icon": "https://is1-ssl.mzstatic.com/image/thumb/Purple221/v4/c9/77/89/c97789e7-5e02-2424-661f-149cfa323dcb/AppIcon-1x_U007ephone-0-1-85-220-0.png/180x180bb.png",
          "rating": 4.6,
          "ratingCount": 36,
          "price": "0.00",
          "rank": 393,
          "category": "6002"
        },
        {
          "appId": 6748551704,
          "name": "Screen Mirroring + Cast To TV",
          "publisher": "CoreBit Solutions",
          "icon": "https://is1-ssl.mzstatic.com/image/thumb/Purple221/v4/37/56/ad/3756adfc-e17f-be60-3617-4d85b5950900/AppIcon-0-0-1x_U007epad-0-1-0-85-220.png/180x180bb.png",
          "rating": 4.7,
          "ratingCount": 623,
          "price": "0.00",
          "rank": 412,
          "category": "6002"
        },
        {
          "appId": 6761622944,
          "name": "The Tea App ·",
          "publisher": "Sahin Bahadir",
          "icon": "https://is1-ssl.mzstatic.com/image/thumb/Purple211/v4/c7/bd/1e/c7bd1eba-a6bd-2abf-b47a-1bfb778445b1/AppIcon-0-0-1x_U007emarketing-0-11-0-85-220.png/180x180bb.png",
          "rating": 0,
          "ratingCount": 0,
          "price": "0.00",
          "rank": 413,
          "category": "6002"
        },
        {
          "appId": 1637883791,
          "name": "Flixtor Movie,Tv Show & series",
          "publisher": "Asmara Nawaz",
          "icon": "https://is1-ssl.mzstatic.com/image/thumb/Purple211/v4/02/b3/57/02b357a8-fcb0-f0ba-3daf-90179acacbbb/AppIcon-0-0-1x_U007emarketing-0-11-0-85-220.png/180x180bb.png",
          "rating": 4,
          "ratingCount": 6138,
          "price": "0.00",
          "rank": 419,
          "category": "6002"
        },
        {
          "appId": 6752599561,
          "name": "LiveLoc: GPS Phone Tracker",
          "publisher": "宏杰 陈",
          "icon": "https://is1-ssl.mzstatic.com/image/thumb/Purple211/v4/28/06/14/28061418-1025-bd0c-4aab-123b4a9c00a6/AppIcon-0-0-1x_U007emarketing-0-7-0-85-220.png/180x180bb.png",
          "rating": 2.5,
          "ratingCount": 4,
          "price": "0.00",
          "rank": 428,
          "category": "6002"
        },
        {
          "appId": 1325003703,
          "name": "Veee+",
          "publisher": "AtomX Ltd.",
          "icon": "https://is1-ssl.mzstatic.com/image/thumb/Purple123/v4/e5/61/99/e56199c4-69c7-608f-1a91-11b6e28d11c3/AppIcon-0-0-1x_U007emarketing-0-0-0-7-0-0-sRGB-0-0-0-GLES2_U002c0-512MB-85-220-0-0.png/180x180bb.png",
          "rating": 4.6,
          "ratingCount": 4746,
          "price": "0.00",
          "rank": 429,
          "category": "6002"
        },
        {
          "appId": 6575352839,
          "name": "SolveLab AI - Smart & Fast",
          "publisher": "玉莹 胡",
          "icon": "https://is1-ssl.mzstatic.com/image/thumb/Purple211/v4/4f/57/33/4f573337-1aa7-26fc-9785-fdcd902582b8/AppIcon-0-0-1x_U007ephone-0-1-0-85-220.png/180x180bb.png",
          "rating": 4.4,
          "ratingCount": 496,
          "price": "0.00",
          "rank": 434,
          "category": "6002"
        },
        {
          "appId": 6759768014,
          "name": "Fuuse",
          "publisher": "Jiangxi Lanshi Cosmetics Co., Ltd",
          "icon": "https://is1-ssl.mzstatic.com/image/thumb/Purple211/v4/f4/17/34/f4173430-8a51-2768-462d-984dbb69695f/AppIcon-1x_U007ephone-0-1-85-220-0.png/180x180bb.png",
          "rating": 4.7,
          "ratingCount": 93,
          "price": "0.00",
          "rank": 437,
          "category": "6002"
        },
        {
          "appId": 6737188111,
          "name": "Owl Translator",
          "publisher": "Seho Energy Co., Limited",
          "icon": "https://is1-ssl.mzstatic.com/image/thumb/Purple211/v4/7b/80/2b/7b802b45-5b83-e493-c8ad-470c2b779bf6/AppIcon-0-0-1x_U007ephone-0-1-0-85-220.png/180x180bb.png",
          "rating": 3.9,
          "ratingCount": 34,
          "price": "0.00",
          "rank": 449,
          "category": "6002"
        },
        {
          "appId": 6747709615,
          "name": "Level Tool · Angle Finder",
          "publisher": "Shenzhen AiPuLeSi Technology Co.,Ltd",
          "icon": "https://is1-ssl.mzstatic.com/image/thumb/Purple221/v4/2a/69/df/2a69df20-36d4-a61c-2708-a264eec4b8e1/AppIcon-0-0-1x_U007ephone-0-1-0-85-220.jpeg/180x180bb.png",
          "rating": 4.5,
          "ratingCount": 186,
          "price": "0.00",
          "rank": 454,
          "category": "6002"
        },
        {
          "appId": 6505110382,
          "name": "Authenticator App • 2FA • MFA",
          "publisher": "RHO APPS",
          "icon": "https://is1-ssl.mzstatic.com/image/thumb/Purple211/v4/ed/16/5e/ed165e12-ff28-3245-d9eb-656eae8fe268/AppIcon1-0-0-1x_U007ephone-0-1-0-85-220.png/180x180bb.png",
          "rating": 4.6,
          "ratingCount": 817,
          "price": "0.00",
          "rank": 456,
          "category": "6002"
        },
        {
          "appId": 6450250043,
          "name": "ZEN PDF PRO",
          "publisher": "EINMOB LIMITED",
          "icon": "https://is1-ssl.mzstatic.com/image/thumb/Purple211/v4/14/ca/38/14ca3813-c121-366e-5504-3fefbb8d7efd/AppIcon-0-0-1x_U007ephone-0-1-0-85-220.png/180x180bb.png",
          "rating": 4.1,
          "ratingCount": 1460,
          "price": "0.00",
          "rank": 459,
          "category": "6002"
        },
        {
          "appId": 6760661036,
          "name": "Domino\\'s Worldwide Rally",
          "publisher": "Domino's Pizza LLC",
          "icon": "https://is1-ssl.mzstatic.com/image/thumb/Purple211/v4/a3/18/d8/a318d870-2924-c8eb-3b5a-bcd98554ca69/AppIcon-0-0-1x_U007emarketing-0-8-0-85-220.png/180x180bb.png",
          "rating": 0,
          "ratingCount": 0,
          "price": "0.00",
          "rank": 461,
          "category": "6002"
        },
        {
          "appId": 6454190738,
          "name": "*** proxy - TipTop ***",
          "publisher": "Free VPN Network",
          "icon": "https://is1-ssl.mzstatic.com/image/thumb/Purple221/v4/28/a2/fe/28a2fe20-dd51-70da-1055-3d3298663a1d/AppIcon-0-0-1x_U007ephone-0-0-85-220.png/100x100bb.jpg",
          "rating": 4.7,
          "ratingCount": 7496,
          "price": "0.00",
          "rank": 463,
          "category": "6002"
        },
        {
          "appId": 6759903740,
          "name": "Site Scanner – Hack Protection",
          "publisher": "Overdrift AB",
          "icon": "https://is1-ssl.mzstatic.com/image/thumb/Purple221/v4/c7/64/97/c764976d-f10b-5ee1-e45c-d094f57d9282/AppIcon-0-0-1x_U007ephone-0-1-0-85-220.jpeg/180x180bb.png",
          "rating": 0,
          "ratingCount": 0,
          "price": "0.00",
          "rank": 465,
          "category": "6002"
        },
        {
          "appId": 6757798015,
          "name": "Scanner : PDF Scanner.",
          "publisher": "Port Canyamel Sociedad Limitada",
          "icon": "https://is1-ssl.mzstatic.com/image/thumb/Purple211/v4/f7/ae/86/f7ae865e-9daa-175e-7a12-e53713a18960/AppIcon-0-0-1x_U007ephone-0-1-0-85-220.jpeg/180x180bb.png",
          "rating": 4.9,
          "ratingCount": 13,
          "price": "0.00",
          "rank": 468,
          "category": "6002"
        },
        {
          "appId": 1056225999,
          "name": "Harris Central Appraisal Dist",
          "publisher": "Clear Village, Inc.",
          "icon": "https://is1-ssl.mzstatic.com/image/thumb/Purple126/v4/ad/ae/6e/adae6eb8-3b39-dfac-79ae-a525cfefae63/AppIcon-0-1x_U007emarketing-0-10-0-85-220.png/180x180bb.png",
          "rating": 2,
          "ratingCount": 192,
          "price": "0.00",
          "rank": 471,
          "category": "6002"
        },
        {
          "appId": 916819108,
          "name": "Gumroad",
          "publisher": "Gumroad",
          "icon": "https://is1-ssl.mzstatic.com/image/thumb/Purple211/v4/ef/8c/ff/ef8cff07-bd9a-0785-d336-2e2b132b9d7b/AppIcon-0-0-1x_U007epad-0-1-85-220.png/180x180bb.png",
          "rating": 4.7,
          "ratingCount": 36800,
          "price": "0.00",
          "rank": 475,
          "category": "6002"
        },
        {
          "appId": 6443335504,
          "name": "NEXT+",
          "publisher": "Sultan ALGhaithi",
          "icon": "https://is1-ssl.mzstatic.com/image/thumb/Purple211/v4/a7/e1/de/a7e1def6-790e-123c-33ae-e40d5d9f3bd4/AppIcon-0-0-1x_U007epad-0-1-85-220.png/180x180bb.png",
          "rating": 4.7,
          "ratingCount": 42,
          "price": "0.00",
          "rank": 476,
          "category": "6002"
        },
        {
          "appId": 6756888991,
          "name": "MyFision",
          "publisher": "Hotwire Communications, Ltd",
          "icon": "https://is1-ssl.mzstatic.com/image/thumb/Purple211/v4/f4/19/70/f4197054-3c5c-9d31-6dc2-fa7b8c638580/AppIcon-0-0-1x_U007ephone-0-1-85-220.png/180x180bb.png",
          "rating": 4.4,
          "ratingCount": 13,
          "price": "0.00",
          "rank": 479,
          "category": "6002"
        },
        {
          "appId": 6450534064,
          "name": "Streisand",
          "publisher": "ARCADIA ODYSSEY INC.",
          "icon": "https://is1-ssl.mzstatic.com/image/thumb/Purple211/v4/a5/e3/19/a5e31997-25cc-0ac6-c025-ecef2550e1c0/AppIcon-0-0-1x_U007epad-0-0-0-1-0-85-220.png/180x180bb.png",
          "rating": 4.4,
          "ratingCount": 1944,
          "price": "0.00",
          "rank": 480,
          "category": "6002"
        },
        {
          "appId": 6449489581,
          "name": "Clean Storage: Master Cleaner",
          "publisher": "KM MOBILE LTD",
          "icon": "https://is1-ssl.mzstatic.com/image/thumb/Purple211/v4/42/1b/ca/421bcab0-7727-458e-b9e6-50d7835247be/AppIcon-0-0-1x_U007emarketing-0-7-0-85-220.png/180x180bb.png",
          "rating": 4.5,
          "ratingCount": 7007,
          "price": "0.00",
          "rank": 482,
          "category": "6002"
        },
        {
          "appId": 1342763352,
          "name": "FoxFM - Offline Video Player",
          "publisher": "Erdem Erciyas",
          "icon": "https://is1-ssl.mzstatic.com/image/thumb/Purple221/v4/03/5e/33/035e335a-23dc-c96c-a7f7-613a1f5b65a1/AppIconFox-0-0-1x_U007emarketing-0-8-0-sRGB-85-220.png/180x180bb.png",
          "rating": 4.4,
          "ratingCount": 28400,
          "price": "0.00",
          "rank": 489,
          "category": "6002"
        },
        {
          "appId": 1618096210,
          "name": "Дядя Ваня ***",
          "publisher": "KONDAKOV OOO",
          "icon": "https://is1-ssl.mzstatic.com/image/thumb/Purple126/v4/48/4b/dd/484bdde3-0280-351c-e0db-b73b21408af5/AppIcon-0-0-1x_U007emarketing-0-10-0-0-85-220.png/180x180bb.png",
          "rating": 4.6,
          "ratingCount": 1614,
          "price": "0.00",
          "rank": 491,
          "category": "6002"
        },
        {
          "appId": 1464980663,
          "name": "Property Assistant by Flyreel",
          "publisher": "Flyreel",
          "icon": "https://is1-ssl.mzstatic.com/image/thumb/Purple211/v4/ee/3f/d0/ee3fd053-982f-9e9b-c354-efcfb38c95f6/AppIcon-0-0-1x_U007emarketing-0-11-0-85-220.png/180x180bb.png",
          "rating": 4.9,
          "ratingCount": 11500,
          "price": "0.00",
          "rank": 492,
          "category": "6002"
        },
        {
          "appId": 1449597018,
          "name": "Atly – Know where to go",
          "publisher": "STEPS Ltd.",
          "icon": "https://is1-ssl.mzstatic.com/image/thumb/Purple211/v4/a9/db/18/a9db1835-df12-e989-8611-6df6e5d1213c/AppIcon-0-0-1x_U007ephone-0-1-85-220.png/180x180bb.png",
          "rating": 4.4,
          "ratingCount": 157,
          "price": "0.00",
          "rank": 493,
          "category": "6002"
        },
        {
          "appId": 6758595813,
          "name": "*** - Plane *** Fly",
          "publisher": "FREE VPNFLY Lab",
          "icon": "https://is1-ssl.mzstatic.com/image/thumb/Purple211/v4/5b/25/27/5b25279b-c84a-0cd4-b85b-f631cb8152f8/AppIcon-0-0-1x_U007ephone-0-1-0-85-220.jpeg/180x180bb.png",
          "rating": 4.6,
          "ratingCount": 296,
          "price": "0.00",
          "rank": 496,
          "category": "6002"
        },
        {
          "appId": 513836029,
          "name": "中国电信-全国统一官方服务平台",
          "publisher": "CHINA TELECOM Corporation Ltd.",
          "icon": "https://is1-ssl.mzstatic.com/image/thumb/Purple221/v4/12/3f/33/123f335c-d7a5-88b9-99a6-71e48ae34227/AppIcon-0-0-1x_U007ephone-0-1-0-0-sRGB-85-220.png/180x180bb.png",
          "rating": 4.3,
          "ratingCount": 7134,
          "price": "0.00",
          "rank": 497,
          "category": "6002"
        },
        {
          "appId": 6502806170,
          "name": "Speed Test & Wi-Fi Analyzer",
          "publisher": "Huacen Co.,LTD",
          "icon": "https://is1-ssl.mzstatic.com/image/thumb/Purple211/v4/af/bc/a2/afbca253-00fa-5d09-01d6-32a1cebf3095/AppIcon-base-0-0-1x_U007epad-0-1-85-220.png/180x180bb.png",
          "rating": 4.7,
          "ratingCount": 149,
          "price": "0.00",
          "rank": 498,
          "category": "6002"
        },
        {
          "appId": 979401801,
          "name": "Browser and Documents Manager",
          "publisher": "Download Apps",
          "icon": "https://is1-ssl.mzstatic.com/image/thumb/Purple123/v4/08/88/f1/0888f1e3-da8d-9c44-187a-dee92acdf2e7/AppIcon-0-1x_U007emarketing-0-0-GLES2_U002c0-512MB-sRGB-0-0-0-85-220-0-0-0-4.png/180x180bb.png",
          "rating": 4.6,
          "ratingCount": 123000,
          "price": "0.00",
          "rank": 499,
          "category": "6002"
        }
      ]
    }
  }
}