{
  "date": "2025-06-23",
  "changes": {
    "6002": {
      "added": [
        {
          "appId": 989212129,
          "name": "iRAR - zip,rar,7z file opener",
          "publisher": "书敏 贾",
          "icon": "https://is1-ssl.mzstatic.com/image/thumb/Purple211/v4/2f/59/de/2f59de89-277a-cec3-269a-778eee0cf449/AppIcon-0-0-1x_U007emarketing-0-7-0-0-85-220.png/180x180bb.png",
          "rating": 4.7,
          "ratingCount": 3712,
          "price": "0.00",
          "rank": 256,
          "category": "6002"
        },
        {
          "appId": 6482850998,
          "name": "RAR & Zip Extractor - AS Unzip",
          "publisher": "东东 杏",
          "icon": "https://is1-ssl.mzstatic.com/image/thumb/Purple221/v4/d4/f4/68/d4f46882-eeb8-9dde-c6cd-be2f718515a1/AppIcon-0-0-1x_U007emarketing-0-10-0-85-220.png/180x180bb.png",
          "rating": 0,
          "ratingCount": 0,
          "price": "0.00",
          "rank": 291,
          "category": "6002"
        },
        {
          "appId": 1503113003,
          "name": "Radio App - Simple Radio Tuner",
          "publisher": "TCV Technology Co., Ltd",
          "icon": "https://is1-ssl.mzstatic.com/image/thumb/Purple221/v4/01/8c/f7/018cf7dc-ce62-003a-abcc-b28c9823e0fc/AppIcon-1-0-0-1x_U007emarketing-0-7-0-sRGB-85-220.png/180x180bb.png",
          "rating": 4.3,
          "ratingCount": 13000,
          "price": "0.00",
          "rank": 298,
          "category": "6002"
        },
        {
          "appId": 1539261586,
          "name": "App *** - Super Fast Unlimited",
          "publisher": "Business Suite Apps Maker for Free",
          "icon": "https://is1-ssl.mzstatic.com/image/thumb/Purple221/v4/06/0e/91/060e9102-0b20-3989-79a4-e0c1388a1841/AppIcon-0-0-1x_U007epad-0-0-85-220.png/180x180bb.png",
          "rating": 4.4,
          "ratingCount": 4463,
          "price": "0.00",
          "rank": 353,
          "category": "6002"
        },
        {
          "appId": 6444063256,
          "name": "PDF Space File - Scan Edit",
          "publisher": "JOYWE TECH PTE. LTD.",
          "icon": "https://is1-ssl.mzstatic.com/image/thumb/Purple221/v4/f6/79/1f/f6791f21-069e-7b7b-d7d0-ce722f084113/AppIcon-0-0-1x_U007ephone-0-1-0-0-85-220.png/180x180bb.png",
          "rating": 4.3,
          "ratingCount": 61,
          "price": "0.00",
          "rank": 371,
          "category": "6002"
        },
        {
          "appId": 479282584,
          "name": "Make It Big",
          "publisher": "An Trinh",
          "icon": "https://is1-ssl.mzstatic.com/image/thumb/Purple112/v4/80/82/a1/8082a1f9-5632-9c3d-4efa-9f4d242a918d/AppIcon-1x_U007emarketing-0-7-0-85-220.png/180x180bb.png",
          "rating": 4.8,
          "ratingCount": 4788,
          "price": "0.00",
          "rank": 373,
          "category": "6002"
        },
        {
          "appId": 6443862073,
          "name": "LED Scroller and Text Banner",
          "publisher": "WHATSTICKER APPS SRL",
          "icon": "https://is1-ssl.mzstatic.com/image/thumb/Purple221/v4/60/54/cf/6054cf87-faa8-b4a6-999d-59b58ae02421/AppIcon4-0-0-1x_U007emarketing-0-7-0-85-220.png/180x180bb.png",
          "rating": 4.7,
          "ratingCount": 2796,
          "price": "0.00",
          "rank": 391,
          "category": "6002"
        },
        {
          "appId": 6746311432,
          "name": "Petmore",
          "publisher": "德志 欧",
          "icon": "https://is1-ssl.mzstatic.com/image/thumb/Purple221/v4/64/fd/17/64fd17f1-7db8-e5e1-252c-9fa483a667e2/AppIcon-1x_U007epad-0-1-0-85-220-0.png/180x180bb.png",
          "rating": 0,
          "ratingCount": 0,
          "price": "0.00",
          "rank": 403,
          "category": "6002"
        },
        {
          "appId": 6503637011,
          "name": "Privacy Pro *** - Wifi & Proxy",
          "publisher": "WidgetPRO",
          "icon": "https://is1-ssl.mzstatic.com/image/thumb/Purple211/v4/f9/bf/60/f9bf60d5-abce-f370-d001-2f252a1ecb1f/AppIcon-0-0-1x_U007emarketing-0-6-0-85-220.png/180x180bb.png",
          "rating": 3.9,
          "ratingCount": 376,
          "price": "0.00",
          "rank": 406,
          "category": "6002"
        },
        {
          "appId": 1484289588,
          "name": "Stud Finder®",
          "publisher": "Tue Nguyen Minh",
          "icon": "https://is1-ssl.mzstatic.com/image/thumb/Purple211/v4/34/80/b7/3480b7f6-4302-d4f5-787a-e2b34022d7a6/Metal_Detector-1x_U007emarketing-0-7-0-85-220-0.jpeg/180x180bb.png",
          "rating": 4.4,
          "ratingCount": 21600,
          "price": "0.00",
          "rank": 421,
          "category": "6002"
        },
        {
          "appId": 1621229655,
          "name": "Sony | BRAVIA Connect",
          "publisher": "Sony Corporation",
          "icon": "https://is1-ssl.mzstatic.com/image/thumb/Purple211/v4/ff/ea/4a/ffea4a14-3b6e-1d2c-5141-699fc6a78743/AppIcon-0-0-1x_U007emarketing-0-11-0-85-220.png/180x180bb.png",
          "rating": 4.5,
          "ratingCount": 3271,
          "price": "0.00",
          "rank": 426,
          "category": "6002"
        },
        {
          "appId": 6737916371,
          "name": "Qr Code Master *",
          "publisher": "Tiki Media LTS",
          "icon": "https://is1-ssl.mzstatic.com/image/thumb/Purple211/v4/9c/8b/07/9c8b078a-fdf5-6dec-907d-94c8aab1fd95/AppIcon-0-0-1x_U007ephone-0-1-0-85-220.png/180x180bb.png",
          "rating": 4.5,
          "ratingCount": 398,
          "price": "0.00",
          "rank": 428,
          "category": "6002"
        },
        {
          "appId": 1490517668,
          "name": "ThermoPro BBQ",
          "publisher": "iTronics Co., Limited",
          "icon": "https://is1-ssl.mzstatic.com/image/thumb/Purple221/v4/3f/d3/03/3fd30391-d672-e34b-3f81-b1a95628f9de/AppIcon-0-0-1x_U007emarketing-0-7-0-85-220.png/180x180bb.png",
          "rating": 4.7,
          "ratingCount": 18400,
          "price": "0.00",
          "rank": 430,
          "category": "6002"
        },
        {
          "appId": 1143920524,
          "name": "Poke Genie -Remote Raid IV PvP",
          "publisher": "Poke Genie Inc.",
          "icon": "https://is1-ssl.mzstatic.com/image/thumb/Purple211/v4/de/2c/a3/de2ca370-dd4a-3f2e-7fd0-3caf53c843ca/AppIcon-0-0-1x_U007emarketing-0-5-85-220.png/180x180bb.png",
          "rating": 4.8,
          "ratingCount": 146000,
          "price": "0.00",
          "rank": 435,
          "category": "6002"
        },
        {
          "appId": 6467768006,
          "name": "Parcel Pending PLUS",
          "publisher": "Neopost Shipping",
          "icon": "https://is1-ssl.mzstatic.com/image/thumb/Purple211/v4/7a/79/3e/7a793eec-dd01-777e-a1df-f572606e5104/AppIcon-1x_U007emarketing-0-10-0-85-220-0.png/180x180bb.png",
          "rating": 3.6,
          "ratingCount": 64,
          "price": "0.00",
          "rank": 445,
          "category": "6002"
        },
        {
          "appId": 6670467628,
          "name": "Universal Remote for Smart TV!",
          "publisher": "Xleum",
          "icon": "https://is1-ssl.mzstatic.com/image/thumb/Purple211/v4/45/ff/dd/45ffdddf-4e47-5edf-5072-881bdf1e0e5c/AppIcon-0-0-1x_U007epad-0-1-0-0-85-220.jpeg/180x180bb.png",
          "rating": 4.8,
          "ratingCount": 1333,
          "price": "0.00",
          "rank": 448,
          "category": "6002"
        },
        {
          "appId": 6473000053,
          "name": "Momcozy",
          "publisher": "HONG KONG LUTE TECHNOLOGY CO., LIMITED",
          "icon": "https://is1-ssl.mzstatic.com/image/thumb/Purple221/v4/f6/9d/de/f69dde3f-8f3b-bf84-3dfe-70f0690e28b6/AppIcon-0-0-1x_U007ephone-0-1-0-sRGB-85-220.png/180x180bb.png",
          "rating": 2.5,
          "ratingCount": 68,
          "price": "0.00",
          "rank": 451,
          "category": "6002"
        },
        {
          "appId": 6744012640,
          "name": "Speed Cleaner: AI Phone Clean",
          "publisher": "INNOMOBI TECHNOLOGY LIMITED",
          "icon": "https://is1-ssl.mzstatic.com/image/thumb/Purple211/v4/81/fb/fd/81fbfde6-4193-46a2-1fb8-85f7b3f1a3e0/AppIcon-0-0-1x_U007ephone-0-1-0-sRGB-85-220.png/180x180bb.png",
          "rating": 4.2,
          "ratingCount": 168,
          "price": "0.00",
          "rank": 456,
          "category": "6002"
        },
        {
          "appId": 6498549218,
          "name": "Stayconnect With TV: Miracast",
          "publisher": "Hang Nguyen",
          "icon": "https://is1-ssl.mzstatic.com/image/thumb/Purple221/v4/cb/f0/88/cbf08840-107f-0a9f-98f5-7d01ad7af7ec/AppIcon-0-0-1x_U007emarketing-0-7-0-sRGB-85-220.png/180x180bb.png",
          "rating": 4.5,
          "ratingCount": 151,
          "price": "0.00",
          "rank": 457,
          "category": "6002"
        },
        {
          "appId": 6740606447,
          "name": "AI Identifier: All-in-One Tool",
          "publisher": "亚飞 陕",
          "icon": "https://is1-ssl.mzstatic.com/image/thumb/Purple221/v4/33/26/cc/3326cc5f-681e-4c05-623d-576cfe108d91/AppIcon-0-0-1x_U007ephone-0-1-0-85-220.png/180x180bb.png",
          "rating": 3,
          "ratingCount": 6,
          "price": "0.00",
          "rank": 459,
          "category": "6002"
        },
        {
          "appId": 6740012766,
          "name": "Flashlight◉ - Magnifying Glass",
          "publisher": "Changsha Shenguangyuan Technology Co., Ltd.",
          "icon": "https://is1-ssl.mzstatic.com/image/thumb/Purple221/v4/de/32/f4/de32f4a0-147a-49c1-399f-9859522d8e0d/AppIcon-0-0-1x_U007emarketing-0-11-0-85-220.png/180x180bb.png",
          "rating": 4.6,
          "ratingCount": 1705,
          "price": "0.00",
          "rank": 469,
          "category": "6002"
        },
        {
          "appId": 6742109546,
          "name": "SecureSurf ***",
          "publisher": "Afshar Enterprises LLC",
          "icon": "https://is1-ssl.mzstatic.com/image/thumb/Purple211/v4/4a/e6/8f/4ae68f7a-15f2-d9c5-16f1-5ded2d09c9a2/AppIcon-1x_U007ephone-0-0-85-220-0.png/180x180bb.png",
          "rating": 4.3,
          "ratingCount": 473,
          "price": "0.00",
          "rank": 471,
          "category": "6002"
        },
        {
          "appId": 368483462,
          "name": "Private Browsing Web Browser",
          "publisher": "SavySoda",
          "icon": "https://is1-ssl.mzstatic.com/image/thumb/Purple211/v4/27/f9/19/27f9198f-30ec-1598-99d2-16a111e71920/PrivateBrowsingAppIcon-0-0-1x_U007emarketing-0-10-0-85-220.png/180x180bb.png",
          "rating": 4.7,
          "ratingCount": 123000,
          "price": "0.00",
          "rank": 472,
          "category": "6002"
        },
        {
          "appId": 1096545820,
          "name": "NIOSH Sound Level Meter",
          "publisher": "EA LAB",
          "icon": "https://is1-ssl.mzstatic.com/image/thumb/Purple113/v4/1e/17/9b/1e179b2d-a642-af2b-f2ec-e36db1fe8563/AppIcon-0-0-1x_U007emarketing-0-0-0-5-0-0-sRGB-0-0-0-GLES2_U002c0-512MB-85-220-0-0.png/180x180bb.png",
          "rating": 4.7,
          "ratingCount": 14600,
          "price": "0.00",
          "rank": 478,
          "category": "6002"
        },
        {
          "appId": 979401801,
          "name": "Browser and Documents Manager",
          "publisher": "Download Apps",
          "icon": "https://is1-ssl.mzstatic.com/image/thumb/Purple123/v4/08/88/f1/0888f1e3-da8d-9c44-187a-dee92acdf2e7/AppIcon-0-1x_U007emarketing-0-0-GLES2_U002c0-512MB-sRGB-0-0-0-85-220-0-0-0-4.png/180x180bb.png",
          "rating": 4.6,
          "ratingCount": 123000,
          "price": "0.00",
          "rank": 480,
          "category": "6002"
        },
        {
          "appId": 1557454007,
          "name": "Smart TV Remote for Samsung",
          "publisher": "Companjen Apps B.V.",
          "icon": "https://is1-ssl.mzstatic.com/image/thumb/Purple211/v4/ed/8d/77/ed8d7743-9d5e-6896-2711-c75534521ca6/AppIcon-0-0-1x_U007emarketing-0-11-0-85-220.png/180x180bb.png",
          "rating": 4.4,
          "ratingCount": 6950,
          "price": "0.00",
          "rank": 484,
          "category": "6002"
        },
        {
          "appId": 6746968850,
          "name": "Sniffles: Studio",
          "publisher": "Denis Ghita",
          "icon": "https://is1-ssl.mzstatic.com/image/thumb/Purple211/v4/ab/99/cd/ab99cd28-e67b-e4cb-9176-65afe2214c5a/AppIcon-0-0-1x_U007emarketing-0-7-0-0-85-220.png/180x180bb.png",
          "rating": 0,
          "ratingCount": 0,
          "price": "0.00",
          "rank": 486,
          "category": "6002"
        },
        {
          "appId": 1561954125,
          "name": "Smart Remote for Sam TV",
          "publisher": "EVOLLY.APP",
          "icon": "https://is1-ssl.mzstatic.com/image/thumb/Purple221/v4/7e/d8/50/7ed85068-7705-f65d-da71-44842ca5f244/AppIcon-0-0-1x_U007emarketing-0-7-0-85-220.png/180x180bb.png",
          "rating": 4.2,
          "ratingCount": 6399,
          "price": "0.00",
          "rank": 488,
          "category": "6002"
        },
        {
          "appId": 1147215836,
          "name": "iTrainer Dog Whistle & Clicker",
          "publisher": "Jade Lizard Software LLC",
          "icon": "https://is1-ssl.mzstatic.com/image/thumb/Purple221/v4/a7/da/0f/a7da0fdd-315c-d269-062f-81ac992c3abb/AppIcon-0-0-1x_U007epad-0-0-0-1-0-85-220.png/180x180bb.png",
          "rating": 4.5,
          "ratingCount": 32200.000000000004,
          "price": "0.00",
          "rank": 489,
          "category": "6002"
        },
        {
          "appId": 6745824119,
          "name": "Charades: Party & Group Games",
          "publisher": "Giorgi Galuashvili",
          "icon": "https://is1-ssl.mzstatic.com/image/thumb/Purple221/v4/0a/5e/ba/0a5eba85-7e43-5571-2d86-b7b418cd3367/AppIcon-0-0-1x_U007epad-0-1-0-85-220.png/180x180bb.png",
          "rating": 5,
          "ratingCount": 1,
          "price": "0.00",
          "rank": 491,
          "category": "6002"
        },
        {
          "appId": 6467652964,
          "name": "Clean Phone Storage Now",
          "publisher": "East End Technologies Ltd.",
          "icon": "https://is1-ssl.mzstatic.com/image/thumb/Purple211/v4/cd/37/d3/cd37d38a-827a-d261-57e3-729d18f917e2/AppIcon-0-1x_U007ephone-0-1-0-0-85-220-0.png/180x180bb.png",
          "rating": 4.6,
          "ratingCount": 5983,
          "price": "0.00",
          "rank": 494,
          "category": "6002"
        },
        {
          "appId": 6473670884,
          "name": "Birdty",
          "publisher": "POCKET INC",
          "icon": "https://is1-ssl.mzstatic.com/image/thumb/Purple211/v4/76/6a/92/766a9210-3c39-1574-769a-0fe85cc87bb1/AppIcon-0-0-1x_U007emarketing-0-8-0-85-220.png/180x180bb.png",
          "rating": 1.9,
          "ratingCount": 52,
          "price": "0.00",
          "rank": 497,
          "category": "6002"
        },
        {
          "appId": 6746046203,
          "name": "Remote for Hisense TV App",
          "publisher": "Ramos Remie",
          "icon": "https://is1-ssl.mzstatic.com/image/thumb/Purple221/v4/48/1d/2e/481d2e13-7e7f-dc03-3f1e-3845899efd32/AppIcon-0-0-1x_U007emarketing-0-7-0-85-220.png/180x180bb.png",
          "rating": 4.8,
          "ratingCount": 87,
          "price": "0.00",
          "rank": 498,
          "category": "6002"
        },
        {
          "appId": 1492560451,
          "name": "KeyConnect Digital Car Key",
          "publisher": "Kain Suite Pte. Ltd.",
          "icon": "https://is1-ssl.mzstatic.com/image/thumb/Purple221/v4/34/8b/00/348b0097-7734-5627-c002-63d911322cdc/Appicon-0-0-1x_U007epad-0-1-0-P3-85-220.png/180x180bb.png",
          "rating": 4.6,
          "ratingCount": 63300,
          "price": "0.00",
          "rank": 499,
          "category": "6002"
        },
        {
          "appId": 6547832056,
          "name": "XB | Controller App For Xbox",
          "publisher": "Jonathon Tufts",
          "icon": "https://is1-ssl.mzstatic.com/image/thumb/Purple211/v4/ae/e9/08/aee908a7-8945-b9fb-df87-734fe2e51dd2/AppIcon-0-0-1x_U007epad-0-85-220.png/180x180bb.png",
          "rating": 4.5,
          "ratingCount": 885,
          "price": "0.00",
          "rank": 500,
          "category": "6002"
        }
      ],
      "removed": [
        {
          "appId": 6480213347,
          "name": "GVRD Pro: Security Tool",
          "publisher": "HRZ TECH LTD",
          "icon": "https://is1-ssl.mzstatic.com/image/thumb/Purple211/v4/81/55/26/81552650-1625-4e43-39be-4bf9025a4283/AppIcon-1x_U007ephone-0-1-0-85-220-0.png/180x180bb.png",
          "rating": 4.3,
          "ratingCount": 287,
          "price": "0.00",
          "rank": 278,
          "category": "6002"
        },
        {
          "appId": 6744103518,
          "name": "Device Armor - Protectiva",
          "publisher": "ENIM WHOLESALE LIMITED",
          "icon": "https://is1-ssl.mzstatic.com/image/thumb/Purple221/v4/10/ea/f4/10eaf4d9-9f00-984c-8bc5-fdf69ffa2007/AppIcon-0-0-1x_U007ephone-0-1-0-85-220.png/180x180bb.png",
          "rating": 4.6,
          "ratingCount": 63,
          "price": "0.00",
          "rank": 313,
          "category": "6002"
        },
        {
          "appId": 6503049207,
          "name": "Find Lost Device, BLE Finder",
          "publisher": "Danny Cerny",
          "icon": "https://is1-ssl.mzstatic.com/image/thumb/Purple221/v4/0d/46/45/0d4645c9-d9a1-0978-626f-776c5055c8c6/AppIcon-1x_U007emarketing-0-10-0-85-220-0.png/180x180bb.png",
          "rating": 4.4,
          "ratingCount": 75,
          "price": "0.00",
          "rank": 321,
          "category": "6002"
        },
        {
          "appId": 6503810233,
          "name": "Remote for Roku TV Control·",
          "publisher": "SEAMOBI TECH PTE LTD",
          "icon": "https://is1-ssl.mzstatic.com/image/thumb/Purple221/v4/23/2c/8b/232c8bf1-8da4-76be-6254-584602b460be/AppIcon-0-0-1x_U007ephone-0-1-0-85-220.png/180x180bb.png",
          "rating": 4.6,
          "ratingCount": 1609,
          "price": "0.00",
          "rank": 340,
          "category": "6002"
        },
        {
          "appId": 6744611876,
          "name": "Math homework Solver & Helper",
          "publisher": "Vadym Karavanov",
          "icon": "https://is1-ssl.mzstatic.com/image/thumb/Purple211/v4/56/29/e6/5629e667-873b-14bb-2a5d-a6d1c8d547d2/AppIcon-0-0-1x_U007ephone-0-1-0-85-220.jpeg/180x180bb.png",
          "rating": 0,
          "ratingCount": 0,
          "price": "0.00",
          "rank": 369,
          "category": "6002"
        },
        {
          "appId": 6670608043,
          "name": "CasesMaster",
          "publisher": "Techno GYM Inc.",
          "icon": "https://is1-ssl.mzstatic.com/image/thumb/Purple221/v4/7e/db/cd/7edbcd70-b186-ff99-4d4c-ed8ccfee5f36/AppIcon-0-0-1x_U007epad-0-1-0-85-220.jpeg/180x180bb.png",
          "rating": 4.3,
          "ratingCount": 32,
          "price": "0.00",
          "rank": 392,
          "category": "6002"
        },
        {
          "appId": 1615561965,
          "name": "RealCall - Spam Call Blocker",
          "publisher": "Second Phone Number Inc",
          "icon": "https://is1-ssl.mzstatic.com/image/thumb/Purple221/v4/f1/4a/02/f14a02de-5408-67b7-5ef7-d1126a69e5cc/AppIcon-0-0-1x_U007emarketing-0-7-0-85-220.png/180x180bb.png",
          "rating": 4.5,
          "ratingCount": 19000,
          "price": "0.00",
          "rank": 405,
          "category": "6002"
        },
        {
          "appId": 6744279441,
          "name": "Clean Wave - Speaker Cleaner",
          "publisher": "Murat Cetin",
          "icon": "https://is1-ssl.mzstatic.com/image/thumb/Purple221/v4/ce/6f/95/ce6f9524-3bfe-c513-f7fe-7ad48d2133d1/prodAppIcon-0-0-1x_U007emarketing-0-8-0-0-85-220.png/180x180bb.png",
          "rating": 0,
          "ratingCount": 0,
          "price": "0.00",
          "rank": 410,
          "category": "6002"
        },
        {
          "appId": 6739242033,
          "name": "CleanerGo: Free up space",
          "publisher": "Delvri Limited",
          "icon": "https://is1-ssl.mzstatic.com/image/thumb/Purple211/v4/49/fc/32/49fc320c-7e0b-f1cd-8567-284003f2f603/AppIcon-0-0-1x_U007epad-0-11-0-85-220.png/180x180bb.png",
          "rating": 4.1,
          "ratingCount": 182,
          "price": "0.00",
          "rank": 418,
          "category": "6002"
        },
        {
          "appId": 6468995505,
          "name": "Safe Security App",
          "publisher": "Tools Tribe",
          "icon": "https://is1-ssl.mzstatic.com/image/thumb/Purple211/v4/ec/7e/8e/ec7e8e76-163e-79c0-31ed-2848f7ea4e5a/AppIcon-0-0-1x_U007epad-0-0-85-220.png/180x180bb.png",
          "rating": 4.4,
          "ratingCount": 4326,
          "price": "0.00",
          "rank": 421,
          "category": "6002"
        },
        {
          "appId": 6448928883,
          "name": "AI Picture Answer: ThinkAssist",
          "publisher": "Zoltan Dross",
          "icon": "https://is1-ssl.mzstatic.com/image/thumb/Purple211/v4/a6/5f/6c/a65f6c51-39f6-b899-9893-d1480fb53fd7/AppIcon-0-0-1x_U007epad-0-1-85-220.jpeg/180x180bb.png",
          "rating": 5,
          "ratingCount": 7,
          "price": "0.00",
          "rank": 426,
          "category": "6002"
        },
        {
          "appId": 661269562,
          "name": "LogMeIn Rescue Customer",
          "publisher": "GoTo Group, Inc.",
          "icon": "https://is1-ssl.mzstatic.com/image/thumb/Purple221/v4/9f/2d/09/9f2d099b-b6a1-0348-6304-6ad00e978798/AppIcon-0-1x_U007epad-0-1-0-85-220-0.png/180x180bb.png",
          "rating": 1.9,
          "ratingCount": 318,
          "price": "0.00",
          "rank": 441,
          "category": "6002"
        },
        {
          "appId": 1462268018,
          "name": "My Airtel Africa",
          "publisher": "Airtel Africa",
          "icon": "https://is1-ssl.mzstatic.com/image/thumb/Purple211/v4/f3/71/69/f371698d-9eeb-6b3c-2f7e-0cf0a90f6ad4/AppIcon-0-1x_U007emarketing-0-6-0-0-sRGB-85-220-0.png/180x180bb.png",
          "rating": 4.1,
          "ratingCount": 3536,
          "price": "0.00",
          "rank": 443,
          "category": "6002"
        },
        {
          "appId": 6454190738,
          "name": "*** proxy - TipTop ***",
          "publisher": "Free VPN Network",
          "icon": "https://is1-ssl.mzstatic.com/image/thumb/Purple221/v4/28/a2/fe/28a2fe20-dd51-70da-1055-3d3298663a1d/AppIcon-0-0-1x_U007ephone-0-0-85-220.png/100x100bb.jpg",
          "rating": 4.8,
          "ratingCount": 5278,
          "price": "0.00",
          "rank": 445,
          "category": "6002"
        },
        {
          "appId": 6745866735,
          "name": "Woee",
          "publisher": "Husam TURKER",
          "icon": "https://is1-ssl.mzstatic.com/image/thumb/Purple211/v4/cc/61/30/cc613028-6845-c154-d4dd-923516b7cb55/AppIcon-1x_U007ephone-0-1-85-220-0.png/180x180bb.png",
          "rating": 0,
          "ratingCount": 0,
          "price": "0.00",
          "rank": 446,
          "category": "6002"
        },
        {
          "appId": 6739199415,
          "name": "AI Cleaner：Phone Cleaner",
          "publisher": "Shenzhen Jingguangda Technology Co., Ltd",
          "icon": "https://is1-ssl.mzstatic.com/image/thumb/Purple211/v4/ec/e1/0d/ece10d9f-bc10-a90d-c0de-11a19d9f9696/AppIcon-0-0-1x_U007ephone-0-1-0-85-220.png/180x180bb.png",
          "rating": 4.5,
          "ratingCount": 874,
          "price": "0.00",
          "rank": 452,
          "category": "6002"
        },
        {
          "appId": 6701998270,
          "name": "Global *** Secure Browser",
          "publisher": "MATRIX MOBILE PTE. LTD.",
          "icon": "https://is1-ssl.mzstatic.com/image/thumb/Purple221/v4/c7/8b/ef/c78bef1f-bb4b-8b27-36de-6b4f4ebf18a8/AppIcon-0-0-1x_U007epad-0-1-0-85-220.png/180x180bb.png",
          "rating": 4.5,
          "ratingCount": 1393,
          "price": "0.00",
          "rank": 456,
          "category": "6002"
        },
        {
          "appId": 6744911539,
          "name": "Cardlaxy: Sell Gift Cards",
          "publisher": "Cardlaxy, LLC",
          "icon": "https://is1-ssl.mzstatic.com/image/thumb/Purple221/v4/ea/1e/bb/ea1ebbdf-da0d-fa9d-b03b-391529c3dc79/AppIcon-0-0-1x_U007epad-0-1-85-220.png/180x180bb.png",
          "rating": 4.1,
          "ratingCount": 9,
          "price": "0.00",
          "rank": 460,
          "category": "6002"
        },
        {
          "appId": 1239860606,
          "name": "Potatso",
          "publisher": "Potatso Lab LTD",
          "icon": "https://is1-ssl.mzstatic.com/image/thumb/Purple221/v4/7b/cd/27/7bcd27a8-092c-0e39-6dfd-cc7d24a1a41e/AppIcon-0-0-1x_U007epad-0-1-0-85-220.png/180x180bb.png",
          "rating": 4.5,
          "ratingCount": 6030,
          "price": "0.00",
          "rank": 463,
          "category": "6002"
        },
        {
          "appId": 6744125469,
          "name": "TYPA - Restock Alerts",
          "publisher": "Stockbyte LLC",
          "icon": "https://is1-ssl.mzstatic.com/image/thumb/Purple211/v4/10/a2/2a/10a22a75-4fb6-60d7-d8b2-0c2bb58a5326/AppIcon-0-0-1x_U007epad-0-1-85-220.png/180x180bb.png",
          "rating": 5,
          "ratingCount": 12,
          "price": "0.00",
          "rank": 464,
          "category": "6002"
        },
        {
          "appId": 6450321292,
          "name": "Stray Kids Light Stick V2",
          "publisher": "UMK Entertainment Co., Ltd",
          "icon": "https://is1-ssl.mzstatic.com/image/thumb/Purple211/v4/6a/47/72/6a4772a0-31db-b7ed-f9b3-fb828f1c7c88/AppIcon-0-0-1x_U007ephone-0-85-220.png/180x180bb.png",
          "rating": 3.1,
          "ratingCount": 184,
          "price": "0.00",
          "rank": 467,
          "category": "6002"
        },
        {
          "appId": 1477261074,
          "name": "Verkada Pass",
          "publisher": "Verkada Inc.",
          "icon": "https://is1-ssl.mzstatic.com/image/thumb/Purple211/v4/de/7a/7b/de7a7b7b-c5ff-c06f-1cc2-aa2db93e0c1b/AppIcon-0-1x_U007epad-0-1-85-220-0.png/180x180bb.png",
          "rating": 0,
          "ratingCount": 0,
          "price": "0.00",
          "rank": 468,
          "category": "6002"
        },
        {
          "appId": 6736569131,
          "name": "Screen Mirroring. Smart View",
          "publisher": "Nouman MUHAMMAD",
          "icon": "https://is1-ssl.mzstatic.com/image/thumb/Purple221/v4/38/6e/9d/386e9dbe-3f87-7bde-a74f-cf3cfd6d7265/AppIcon-0-0-1x_U007ephone-0-1-0-85-220.jpeg/180x180bb.png",
          "rating": 4.7,
          "ratingCount": 70,
          "price": "0.00",
          "rank": 469,
          "category": "6002"
        },
        {
          "appId": 6670333179,
          "name": "avo*** - fast & secure *** app",
          "publisher": "Avocado VPN Technologies",
          "icon": "https://is1-ssl.mzstatic.com/image/thumb/Purple211/v4/26/d1/19/26d119af-5eb7-0b49-9b4a-c97a9692cb42/AppIcon-0-0-1x_U007epad-0-1-0-85-220.png/180x180bb.png",
          "rating": 4.3,
          "ratingCount": 18,
          "price": "0.00",
          "rank": 470,
          "category": "6002"
        },
        {
          "appId": 6742160701,
          "name": "PDF Converter: Photo Scanner",
          "publisher": "GERARD MARTINS TIKIJJA",
          "icon": "https://is1-ssl.mzstatic.com/image/thumb/Purple211/v4/b6/88/11/b6881139-4883-525d-940f-a8dd0379245f/AppIcon-0-1x_U007emarketing-0-7-0-85-220-0.png/180x180bb.png",
          "rating": 4.5,
          "ratingCount": 31,
          "price": "0.00",
          "rank": 471,
          "category": "6002"
        },
        {
          "appId": 6502906373,
          "name": "Bluetooth Scanner: Finder App",
          "publisher": "Stefan Arnold",
          "icon": "https://is1-ssl.mzstatic.com/image/thumb/Purple221/v4/c4/a8/9e/c4a89eda-7e7a-4387-6e07-4904ea3a8eec/AppIcon-0-0-1x_U007emarketing-0-10-0-85-220.png/180x180bb.png",
          "rating": 4.5,
          "ratingCount": 142,
          "price": "0.00",
          "rank": 472,
          "category": "6002"
        },
        {
          "appId": 1106069401,
          "name": "Samsara Driver",
          "publisher": "Samsara Networks, Inc.",
          "icon": "https://is1-ssl.mzstatic.com/image/thumb/Purple221/v4/62/d0/8e/62d08ec7-39c8-d96a-2af4-8c83fef7b473/D2AppIcon-1x_U007emarketing-0-8-0-85-220-0.png/180x180bb.png",
          "rating": 4.7,
          "ratingCount": 8817,
          "price": "0.00",
          "rank": 479,
          "category": "6002"
        },
        {
          "appId": 6738350240,
          "name": "True: Caller ID &Number Search",
          "publisher": "Hemil Vasani",
          "icon": "https://is1-ssl.mzstatic.com/image/thumb/Purple221/v4/97/c4/1a/97c41ab8-a525-44cc-7131-5f187d670aed/AppIcon-0-0-1x_U007ephone-0-1-0-85-220.png/180x180bb.png",
          "rating": 4,
          "ratingCount": 66,
          "price": "0.00",
          "rank": 480,
          "category": "6002"
        },
        {
          "appId": 398129933,
          "name": "Calculator₊",
          "publisher": "Impala Studios",
          "icon": "https://is1-ssl.mzstatic.com/image/thumb/Purple211/v4/22/53/4c/22534c25-7091-c0e3-bdc9-b841f0461ce7/AppIcon-0-0-1x_U007epad-0-1-0-P3-0-85-220.png/180x180bb.png",
          "rating": 4.7,
          "ratingCount": 1670000,
          "price": "0.00",
          "rank": 481,
          "category": "6002"
        },
        {
          "appId": 1232419615,
          "name": "McAfee Security for T-Mobile",
          "publisher": "T-Mobile",
          "icon": "https://is1-ssl.mzstatic.com/image/thumb/Purple211/v4/46/c2/41/46c241e1-cd5e-8e63-63c4-bde9b39096c5/AppIcon-0-0-1x_U007emarketing-0-8-0-85-220.png/180x180bb.png",
          "rating": 4.7,
          "ratingCount": 38500,
          "price": "0.00",
          "rank": 483,
          "category": "6002"
        },
        {
          "appId": 787415770,
          "name": "Enphase Enlighten",
          "publisher": "Enphase Energy, Inc.",
          "icon": "https://is1-ssl.mzstatic.com/image/thumb/Purple221/v4/9a/c8/6f/9ac86f90-ebd5-b7bd-c4a3-c4afacd14e40/AppIcon-0-0-1x_U007emarketing-0-11-0-0-0-0-85-220.png/180x180bb.png",
          "rating": 4.6,
          "ratingCount": 80200,
          "price": "0.00",
          "rank": 488,
          "category": "6002"
        },
        {
          "appId": 795721582,
          "name": "Ring Sizer by Jason Withers ©",
          "publisher": "Uniqo Lab.",
          "icon": "https://is1-ssl.mzstatic.com/image/thumb/Purple221/v4/62/68/69/6268696c-b7c7-91fa-852d-a9c647e85db7/AppIcon-0-1x_U007epad-0-0-85-220-0.png/180x180bb.png",
          "rating": 4.6,
          "ratingCount": 4362,
          "price": "0.00",
          "rank": 494,
          "category": "6002"
        },
        {
          "appId": 6469943309,
          "name": "FindSpy Hidden Camera Detector",
          "publisher": "Kain Suite Pte. Ltd.",
          "icon": "https://is1-ssl.mzstatic.com/image/thumb/Purple221/v4/18/42/32/1842329f-28e3-2422-ff04-d0117b754917/AppIcon-0-0-1x_U007epad-0-1-0-sRGB-85-220.jpeg/180x180bb.png",
          "rating": 4.5,
          "ratingCount": 3493,
          "price": "0.00",
          "rank": 496,
          "category": "6002"
        },
        {
          "appId": 6747010736,
          "name": "Racing Top",
          "publisher": "Jagrutiben Gavint",
          "icon": "https://is1-ssl.mzstatic.com/image/thumb/Purple221/v4/dc/0f/22/dc0f226d-7e25-2e08-cd61-006ce89f8599/AppIcon-0-0-1x_U007ephone-0-1-85-220.jpeg/180x180bb.png",
          "rating": 0,
          "ratingCount": 0,
          "price": "0.00",
          "rank": 499,
          "category": "6002"
        },
        {
          "appId": 1534850579,
          "name": "Countdown Buddy",
          "publisher": "Taptics Ltd.",
          "icon": "https://is1-ssl.mzstatic.com/image/thumb/Purple221/v4/89/5d/37/895d3747-b4ae-86ce-e51a-c85073584546/AppIcon-0-0-1x_U007ephone-0-0-0-1-0-0-sRGB-85-220.png/180x180bb.png",
          "rating": 4.7,
          "ratingCount": 19400,
          "price": "0.00",
          "rank": 500,
          "category": "6002"
        }
      ]
    }
  }
}