{
  "date": "2026-02-17",
  "genre": "6012",
  "topRisers": [
    {
      "appId": 6749086361,
      "previous_rank": 393,
      "current_rank": 48,
      "rank_change": 345,
      "category": "6012",
      "date": "2026-02-17",
      "icon": "https://is1-ssl.mzstatic.com/image/thumb/Purple221/v4/82/26/d7/8226d7e7-f48c-35ec-fd09-85096e177177/AppIcon-0-0-1x_U007emarketing-0-7-0-85-220.png/180x180bb.png",
      "app_name": "Pet&more",
      "publisher": "Mechideas"
    },
    {
      "appId": 1495094343,
      "previous_rank": 469,
      "current_rank": 296,
      "rank_change": 173,
      "category": "6012",
      "date": "2026-02-17",
      "icon": "https://is1-ssl.mzstatic.com/image/thumb/Purple211/v4/b5/02/4b/b5024b66-ce03-135e-21c7-42ab882231b4/AppIcon-0-0-1x_U007epad-0-1-0-85-220.png/180x180bb.png",
      "app_name": "Moen Smart Water Network",
      "publisher": "Moen Incorporated"
    },
    {
      "appId": 6756916007,
      "previous_rank": 467,
      "current_rank": 363,
      "rank_change": 104,
      "category": "6012",
      "date": "2026-02-17",
      "icon": "https://is1-ssl.mzstatic.com/image/thumb/Purple221/v4/53/d0/b5/53d0b5b1-275d-01ea-7a4c-4473c01d6a79/AppIcon-0-0-1x_U007ephone-0-1-85-220.png/180x180bb.png",
      "app_name": "Areum",
      "publisher": "Bounty Studio, Inc."
    },
    {
      "appId": 1623569698,
      "previous_rank": 420,
      "current_rank": 318,
      "rank_change": 102,
      "category": "6012",
      "date": "2026-02-17",
      "icon": "https://is1-ssl.mzstatic.com/image/thumb/Purple211/v4/ec/41/a6/ec41a6f2-b2e8-ce70-be18-452a355e60b4/AppIcon-0-0-1x_U007emarketing-0-7-0-85-220.png/180x180bb.png",
      "app_name": "JoinBrands: UGC Creator Jobs",
      "publisher": "Join Brands"
    },
    {
      "appId": 1672660475,
      "previous_rank": 448,
      "current_rank": 351,
      "rank_change": 97,
      "category": "6012",
      "date": "2026-02-17",
      "icon": "https://is1-ssl.mzstatic.com/image/thumb/Purple211/v4/a2/3a/ea/a23aea00-c1f0-7403-49d2-baa85e6ad25f/AppIcon-0-0-1x_U007ephone-0-1-85-220.png/180x180bb.png",
      "app_name": "Kale - Creator Rewards",
      "publisher": "Palette Technologies Inc"
    },
    {
      "appId": 1045548013,
      "previous_rank": 423,
      "current_rank": 332,
      "rank_change": 91,
      "category": "6012",
      "date": "2026-02-17",
      "icon": "https://is1-ssl.mzstatic.com/image/thumb/Purple221/v4/95/7e/b4/957eb4e9-aff5-2ca6-c2a0-c2af0bee7a98/AppIcon-0-0-1x_U007emarketing-0-11-0-0-0-85-220.png/180x180bb.png",
      "app_name": "Roomster",
      "publisher": "Roomster Corp."
    }
  ]
}