{
  "date": "2025-06-11",
  "genre": "6013",
  "topRisers": [
    {
      "appId": 1182030612,
      "previous_rank": 385,
      "current_rank": 218,
      "rank_change": 167,
      "category": "6013",
      "date": "2025-06-11",
      "icon": "https://is1-ssl.mzstatic.com/image/thumb/Purple211/v4/d2/5d/6b/d25d6bd3-63cd-8928-52ec-8a58e45b6bd9/AppIcon-0-0-1x_U007emarketing-0-6-0-85-220.png/180x180bb.png",
      "app_name": "HOTWORX",
      "publisher": "Planet Beach"
    },
    {
      "appId": 6443568264,
      "previous_rank": 491,
      "current_rank": 352,
      "rank_change": 139,
      "category": "6013",
      "date": "2025-06-11",
      "icon": "https://is1-ssl.mzstatic.com/image/thumb/Purple221/v4/47/a5/12/47a512d1-29f1-3d9e-b3fa-fe1638445a6e/AppIcon-0-0-1x_U007epad-0-1-85-220.png/180x180bb.png",
      "app_name": "PetPage",
      "publisher": "AllyDVM"
    },
    {
      "appId": 1464632516,
      "previous_rank": 415,
      "current_rank": 278,
      "rank_change": 137,
      "category": "6013",
      "date": "2025-06-11",
      "icon": "https://is1-ssl.mzstatic.com/image/thumb/Purple211/v4/27/46/57/27465749-aac3-a515-c21e-50afd03b1303/AppIcon-0-0-1x_U007emarketing-0-6-0-85-220.png/180x180bb.png",
      "app_name": "Evolt Active",
      "publisher": "Evolt Active"
    },
    {
      "appId": 6746347927,
      "previous_rank": 352,
      "current_rank": 226,
      "rank_change": 126,
      "category": "6013",
      "date": "2025-06-11",
      "icon": "https://is1-ssl.mzstatic.com/image/thumb/Purple221/v4/d1/ca/da/d1cadaef-5619-7a2f-5387-8b8377adadb1/AppIcon-0-0-1x_U007epad-0-1-0-85-220.png/180x180bb.png",
      "app_name": "Color Sort: Brain Games",
      "publisher": "SocialLoop LLC"
    },
    {
      "appId": 728293729,
      "previous_rank": 486,
      "current_rank": 360,
      "rank_change": 126,
      "category": "6013",
      "date": "2025-06-11",
      "icon": "https://is1-ssl.mzstatic.com/image/thumb/Purple221/v4/d9/ef/cd/d9efcd44-e890-3c28-4f57-3b745dc99b17/AppIcon-0-1x_U007emarketing-0-0-0-6-0-0-85-220-0.png/180x180bb.png",
      "app_name": "Blue Shield of California",
      "publisher": "Blue Shield of California"
    },
    {
      "appId": 931986739,
      "previous_rank": 322,
      "current_rank": 199,
      "rank_change": 123,
      "category": "6013",
      "date": "2025-06-11",
      "icon": "https://is1-ssl.mzstatic.com/image/thumb/Purple221/v4/2a/bc/89/2abc89f7-d513-7509-f24d-0de5dbe786ea/AppIcon-0-0-1x_U007emarketing-0-8-0-85-220.png/180x180bb.png",
      "app_name": "Your Texas Benefits",
      "publisher": "HHSC"
    }
  ]
}